perfect_pypi-0.0.1.12.data/scripts/pfpy
perfect_pypi-0.0.1.12.data/scripts/pfpy.bat
perfect_pypi-0.0.1.12.data/scripts/pfpy.completion.sh
perfectpypi/__init__.py
perfectpypi/__main__.py
perfectpypi/version.py
perfectpypi/core/__init__.py
perfectpypi/core/perfectpypi_core.py
perfectpypi/core/perfectpypi_core_unittest.py
perfect_pypi-0.0.1.12.dist-info/METADATA
perfect_pypi-0.0.1.12.dist-info/WHEEL
perfect_pypi-0.0.1.12.dist-info/top_level.txt
perfect_pypi-0.0.1.12.dist-info/zip-safe
perfect_pypi-0.0.1.12.dist-info/RECORD
