Metadata-Version: 2.1
Name: perfect-pypi
Version: 0.0.1.12
Summary: perfect-pypi - Empty example PYPI package by leecampbellc85
Home-page: https://github.com/leecampbellc85/perfect-pypi
Author: leecampbellc85
Author-email: lee.campbell.c85@hotmail.com
License: MIT
Keywords: python leecampbellc85hu
Platform: UNKNOWN
Classifier: Development Status :: 3 - Alpha
Classifier: Operating System :: Microsoft :: Windows
Classifier: Operating System :: POSIX :: Linux
Classifier: Intended Audience :: Developers
Classifier: Topic :: Software Development :: Build Tools
Classifier: License :: OSI Approved :: MIT License
Classifier: Programming Language :: Python
Classifier: Programming Language :: Python :: 2
Classifier: Programming Language :: Python :: 2.7
Requires-Python: >=2.6, <3
Requires-Dist: docopt
